FlaskChs/README.md
FlaskChs/__init__.py
FlaskChs/__main__.py
FlaskChs/file.epub
FlaskChs/index.html
FlaskChs/css/__init__.py
FlaskChs/css/annotations.css
FlaskChs/css/main.css
FlaskChs/css/normalize.css
FlaskChs/css/popup.css
FlaskChs/font/__init__.py
FlaskChs/font/fontello.eot
FlaskChs/font/fontello.svg
FlaskChs/font/fontello.ttf
FlaskChs/font/fontello.woff
FlaskChs/img/__init__.py
FlaskChs/img/annotator-glyph-sprite.png
FlaskChs/img/annotator-icon-sprite.png
FlaskChs/img/apple-touch-icon.png
FlaskChs/img/cancelfullscreen.png
FlaskChs/img/close.png
FlaskChs/img/fullscreen.png
FlaskChs/img/loader.gif
FlaskChs/img/menu-icon.png
FlaskChs/img/save.png
FlaskChs/img/saved.png
FlaskChs/img/settings-s.png
FlaskChs/img/settings.png
FlaskChs/img/star.png
FlaskChs/js/__init__.py
FlaskChs/js/epub.js
FlaskChs/js/epub.min.js
FlaskChs/js/epub.min.map
FlaskChs/js/hooks.min.js
FlaskChs/js/hooks.min.map
FlaskChs/js/reader.js
FlaskChs/js/reader.js.map
FlaskChs/js/reader.min.js
FlaskChs/js/reader.min.map
FlaskChs/js/hooks/__init__.py
FlaskChs/js/hooks/extensions/__init__.py
FlaskChs/js/hooks/extensions/highlight.js
FlaskChs/js/libs/__init__.py
FlaskChs/js/libs/jquery.min.js
FlaskChs/js/libs/localforage.min.js
FlaskChs/js/libs/screenfull.js
FlaskChs/js/libs/screenfull.min.js
FlaskChs/js/libs/zip.min.js
FlaskChs/js/plugins/__init__.py
FlaskChs/js/plugins/hypothesis.js
FlaskChs/js/plugins/search.js
flask_chs-2024.3.1.0.dist-info/METADATA
flask_chs-2024.3.1.0.dist-info/WHEEL
flask_chs-2024.3.1.0.dist-info/entry_points.txt
flask_chs-2024.3.1.0.dist-info/top_level.txt
flask_chs-2024.3.1.0.dist-info/RECORD
